odoo/addons/ecommerce_connector_sale_order_type/README.rst
odoo/addons/ecommerce_connector_sale_order_type/__init__.py
odoo/addons/ecommerce_connector_sale_order_type/__manifest__.py
odoo/addons/ecommerce_connector_sale_order_type/models/__init__.py
odoo/addons/ecommerce_connector_sale_order_type/models/ecommerce_connection.py
odoo/addons/ecommerce_connector_sale_order_type/models/ecommerce_connector.py
odoo/addons/ecommerce_connector_sale_order_type/readme/CONFIGURE.md
odoo/addons/ecommerce_connector_sale_order_type/readme/CONTRIBUTORS.md
odoo/addons/ecommerce_connector_sale_order_type/readme/DESCRIPTION.md
odoo/addons/ecommerce_connector_sale_order_type/static/description/icon.png
odoo/addons/ecommerce_connector_sale_order_type/static/description/index.html
odoo/addons/ecommerce_connector_sale_order_type/views/ecommerce_connection_views.xml
odoo_addon_ecommerce_connector_sale_order_type-15.0.1.0.0.1.dist-info/METADATA
odoo_addon_ecommerce_connector_sale_order_type-15.0.1.0.0.1.dist-info/WHEEL
odoo_addon_ecommerce_connector_sale_order_type-15.0.1.0.0.1.dist-info/top_level.txt
odoo_addon_ecommerce_connector_sale_order_type-15.0.1.0.0.1.dist-info/RECORD
