Metadata-Version: 2.1
Name: odoo-addon-ecommerce_connector_sale_order_type
Version: 15.0.1.0.0.1
Requires-Python: >=3.8
Requires-Dist: odoo-addon-ecommerce_connector>=15.0dev,<15.1dev
Requires-Dist: odoo-addon-sale_order_type>=15.0dev,<15.1dev
Requires-Dist: odoo>=15.0a,<15.1dev
Summary: Set a default sale type for ecommerce sale orders.
Home-page: https://github.com/sygel-technology/sy-general-connector
License: AGPL-3
Author: Sygel
Classifier: Programming Language :: Python
Classifier: Framework :: Odoo
Classifier: Framework :: Odoo :: 15.0
Classifier: License :: OSI Approved :: GNU Affero General Public License v3
